demo/__init__.py
demo/config.py
demo/demo.py
demo/embeddings.py
demo/main.py
demo/models.py
demo/prompts.py
demo/utils.py
tests/__init__.py
tests/test_demo.py
tests/test_embeddings.py
tests/test_utils.py
uis_sprint_report-2026.1.201651.dist-info/licenses/LICENSE
uis_sprint_report-2026.1.201651.dist-info/METADATA
uis_sprint_report-2026.1.201651.dist-info/WHEEL
uis_sprint_report-2026.1.201651.dist-info/entry_points.txt
uis_sprint_report-2026.1.201651.dist-info/top_level.txt
uis_sprint_report-2026.1.201651.dist-info/RECORD
