Metadata-Version: 2.4
Name: uis-sprint-report
Version: 2026.1.201651
Summary: A Python package for generating sprint reports and managing sprint activities at University Information Services.
Home-page: https://gitlab.developers.cam.ac.uk/ee345/demo
Author: Eugene Evstafev
Author-email: ee345@cam.ac.uk
Classifier: License :: OSI Approved :: MIT License
Classifier: Development Status :: 4 - Beta
Classifier: Intended Audience :: Developers
Classifier: Programming Language :: Python :: 3
Classifier: Operating System :: OS Independent
Requires-Python: >=3.7
License-File: LICENSE
Requires-Dist: click>=8.1.7
Requires-Dist: rich>=13.7.1
Requires-Dist: python-pptx>=0.6.23
Requires-Dist: huggingface-hub==0.23.4
Requires-Dist: langchain==0.2.6
Requires-Dist: langchain-community==0.2.6
Requires-Dist: langchain-core==0.2.10
Requires-Dist: langchain-huggingface==0.0.3
Requires-Dist: langchain-text-splitters==0.2.2
Requires-Dist: faiss-cpu>=1.8.0
Requires-Dist: pydantic>=2.7.4
Requires-Dist: scikit-learn>=0.24.1
Requires-Dist: torch>=1.9.0
Requires-Dist: transformers>=4.42.3
Requires-Dist: ollama==0.2.1
Requires-Dist: get-gitlab-issues
Dynamic: author
Dynamic: author-email
Dynamic: classifier
Dynamic: description
Dynamic: description-content-type
Dynamic: home-page
Dynamic: license-file
Dynamic: requires-dist
Dynamic: requires-python
Dynamic: summary
